odoo8_addon_account_reconcile_prepare_account-8.0.1.0.0.99.dev14-nspkg.pth
odoo_addons/account_reconcile_prepare_account/README.rst
odoo_addons/account_reconcile_prepare_account/__init__.py
odoo_addons/account_reconcile_prepare_account/__openerp__.py
odoo_addons/account_reconcile_prepare_account/i18n/account_reconcile_prepare_account.pot
odoo_addons/account_reconcile_prepare_account/i18n/ca.po
odoo_addons/account_reconcile_prepare_account/i18n/de.po
odoo_addons/account_reconcile_prepare_account/i18n/es.po
odoo_addons/account_reconcile_prepare_account/i18n/es_MX.po
odoo_addons/account_reconcile_prepare_account/i18n/fr.po
odoo_addons/account_reconcile_prepare_account/i18n/gl.po
odoo_addons/account_reconcile_prepare_account/i18n/hr.po
odoo_addons/account_reconcile_prepare_account/i18n/hr_HR.po
odoo_addons/account_reconcile_prepare_account/i18n/hu.po
odoo_addons/account_reconcile_prepare_account/i18n/it.po
odoo_addons/account_reconcile_prepare_account/i18n/nl.po
odoo_addons/account_reconcile_prepare_account/i18n/nl_NL.po
odoo_addons/account_reconcile_prepare_account/i18n/pt.po
odoo_addons/account_reconcile_prepare_account/i18n/pt_BR.po
odoo_addons/account_reconcile_prepare_account/i18n/pt_PT.po
odoo_addons/account_reconcile_prepare_account/i18n/ro_RO.po
odoo_addons/account_reconcile_prepare_account/i18n/sl.po
odoo_addons/account_reconcile_prepare_account/i18n/tr.po
odoo_addons/account_reconcile_prepare_account/models/__init__.py
odoo_addons/account_reconcile_prepare_account/models/account_bank_statement_line.py
odoo_addons/account_reconcile_prepare_account/static/description/icon.png
odoo_addons/account_reconcile_prepare_account/static/src/js/account_reconcile_prepare_account.js
odoo_addons/account_reconcile_prepare_account/views/account_bank_statement.xml
odoo_addons/account_reconcile_prepare_account/views/templates.xml
odoo8_addon_account_reconcile_prepare_account-8.0.1.0.0.99.dev14.dist-info/METADATA
odoo8_addon_account_reconcile_prepare_account-8.0.1.0.0.99.dev14.dist-info/WHEEL
odoo8_addon_account_reconcile_prepare_account-8.0.1.0.0.99.dev14.dist-info/namespace_packages.txt
odoo8_addon_account_reconcile_prepare_account-8.0.1.0.0.99.dev14.dist-info/top_level.txt
odoo8_addon_account_reconcile_prepare_account-8.0.1.0.0.99.dev14.dist-info/RECORD
